[
  {
    "id": "4080036a-392d-4935-a52d-73cd595970f0",
    "title": "Google",
    "method": "GET",
    "host": "http://www.google.com",
    "path": "foo/bar"
  },
  {
    "id": "1821ff4c-dcdc-4bff-87b0-bff4a2f88096",
    "title": "My local server!",
    "method": "POST",
    "host": "http://homeassistant.local",
    "path": "api",
    "headers": {
      "bc695e68-cce0-4f26-b1f4-9c4429e24300": {
        "key": "content-type",
        "value": "application/json"
      },
      "2ae838b9-b2ac-4e6a-a425-5c1626c723b2": {
        "key": "some-other-header",
        "value": "foo"
      }
    }
  },
  {
    "id": "9c0269d2-af41-4718-9f1d-70b4f63ccbf2",
    "title": "Cat Facts",
    "method": "GET",
    "host": "https://meowfacts.herokuapp.com/",
    "path": ""
  }
]
